py4chan
