Metadata-Version: 1.0
Name: py-4chan
Version: 0.2.4
Summary: Python 4chan API Wrapper. Modded by the Bibliotheca Anonoma to support the BA 4chan-thread-archiver
Home-page: http://github.com/bibanon/py-4chan
Author: Edgeworth Euler
Author-email: e@encyclopediadramatica.se
License: http://sam.zoy.org/wtfpl/COPYING
Platform: UNKNOWN
